conf_mat/__init__.py
conf_mat/conf_Mat_Ex.png
conf_mat/conf_mat.py
conf_mat-1.1.0.dist-info/LICENSE
conf_mat-1.1.0.dist-info/METADATA
conf_mat-1.1.0.dist-info/WHEEL
conf_mat-1.1.0.dist-info/top_level.txt
conf_mat-1.1.0.dist-info/RECORD
