Metadata-Version: 2.1
Name: conf-mat
Version: 1.1.0
Summary: Sophisticate Confusion Matrix
Home-page: https://pypi.org/project/conf-mat/
Author: khiat Mohammed Abderrezzak
Author-email: khiat.dev@gmail.com
License: MIT
Keywords: confusion matrix
Classifier: Programming Language :: Python :: 3
Classifier: Operating System :: OS Independent
Classifier: License :: OSI Approved :: MIT License
Requires-Python: >=3.6
License-File: LICENSE
Requires-Dist: matplotlib (>=3.8.3)
Requires-Dist: tabulate (>=0.9.0)
